src/__init__.py
src/main.py
repo_blueprint-1.1.2.dist-info/LICENSE
repo_blueprint-1.1.2.dist-info/METADATA
repo_blueprint-1.1.2.dist-info/WHEEL
repo_blueprint-1.1.2.dist-info/entry_points.txt
repo_blueprint-1.1.2.dist-info/top_level.txt
repo_blueprint-1.1.2.dist-info/RECORD
